celeste_text_generation/__init__.py
celeste_text_generation/client.py
celeste_text_generation/io.py
celeste_text_generation/models.py
celeste_text_generation/parameters.py
celeste_text_generation/py.typed
celeste_text_generation/streaming.py
celeste_text_generation/providers/__init__.py
celeste_text_generation/providers/anthropic/__init__.py
celeste_text_generation/providers/anthropic/client.py
celeste_text_generation/providers/anthropic/models.py
celeste_text_generation/providers/anthropic/parameters.py
celeste_text_generation/providers/anthropic/streaming.py
celeste_text_generation/providers/cohere/__init__.py
celeste_text_generation/providers/cohere/client.py
celeste_text_generation/providers/cohere/models.py
celeste_text_generation/providers/cohere/parameters.py
celeste_text_generation/providers/cohere/streaming.py
celeste_text_generation/providers/google/__init__.py
celeste_text_generation/providers/google/client.py
celeste_text_generation/providers/google/models.py
celeste_text_generation/providers/google/parameters.py
celeste_text_generation/providers/google/streaming.py
celeste_text_generation/providers/mistral/__init__.py
celeste_text_generation/providers/mistral/client.py
celeste_text_generation/providers/mistral/models.py
celeste_text_generation/providers/mistral/parameters.py
celeste_text_generation/providers/mistral/streaming.py
celeste_text_generation/providers/openai/__init__.py
celeste_text_generation/providers/openai/client.py
celeste_text_generation/providers/openai/models.py
celeste_text_generation/providers/openai/parameters.py
celeste_text_generation/providers/openai/streaming.py
celeste_text_generation/providers/xai/__init__.py
celeste_text_generation/providers/xai/client.py
celeste_text_generation/providers/xai/models.py
celeste_text_generation/providers/xai/parameters.py
celeste_text_generation/providers/xai/streaming.py
celeste_text_generation-0.3.8.dist-info/METADATA
celeste_text_generation-0.3.8.dist-info/WHEEL
celeste_text_generation-0.3.8.dist-info/entry_points.txt
celeste_text_generation-0.3.8.dist-info/RECORD
