Metadata-Version: 2.4
Name: celeste-text-generation
Version: 0.3.8
Summary: Text generation package for Celeste AI. Unified interface for all providers
Project-URL: Homepage, https://withceleste.ai
Project-URL: Documentation, https://withceleste.ai/docs
Project-URL: Repository, https://github.com/withceleste/celeste-python
Project-URL: Issues, https://github.com/withceleste/celeste-python/issues
Author-email: Kamilbenkirane <kamil@withceleste.ai>
License: MIT
Keywords: ai,anthropic,claude,cohere,gemini,llm,mistral,openai,text-generation
Classifier: Development Status :: 3 - Alpha
Classifier: Intended Audience :: Developers
Classifier: License :: OSI Approved :: MIT License
Classifier: Operating System :: OS Independent
Classifier: Programming Language :: Python :: 3
Classifier: Programming Language :: Python :: 3.12
Classifier: Programming Language :: Python :: 3.13
Classifier: Topic :: Scientific/Engineering :: Artificial Intelligence
Classifier: Typing :: Typed
Requires-Python: >=3.12
Requires-Dist: celeste-ai>=0.3.3
Requires-Dist: celeste-anthropic>=0.3.3
Requires-Dist: celeste-cohere>=0.3.3
Requires-Dist: celeste-google>=0.3.3
Requires-Dist: celeste-mistral>=0.3.3
Requires-Dist: celeste-openai>=0.3.3
Requires-Dist: celeste-xai>=0.3.3
